pypi_downloader/__init__.py
pypi_downloader/pypi_downloader_mt.py
pypi_downloader/pypi_packages.py
pypi_downloader-2.0.6.dist-info/LICENSE
pypi_downloader-2.0.6.dist-info/METADATA
pypi_downloader-2.0.6.dist-info/WHEEL
pypi_downloader-2.0.6.dist-info/entry_points.txt
pypi_downloader-2.0.6.dist-info/top_level.txt
pypi_downloader-2.0.6.dist-info/RECORD
