Metadata-Version: 2.1
Name: pypi-downloader
Version: 2.0.6
Summary: This project can be used to mirror the pypi index using the new warehouse api.
Author: Patrick Chandler
Author-email: pc.seanmckay@gmail.com
License: GPL3
Requires-Python: >=3.6
License-File: LICENSE
Requires-Dist: certifi ==2024.2.2
Requires-Dist: chardet ==5.2.0
Requires-Dist: charset-normalizer ==3.3.2
Requires-Dist: idna ==3.6
Requires-Dist: lxml ==5.1.0
Requires-Dist: PyYAML ==6.0.1
Requires-Dist: requests ==2.31.0
Requires-Dist: urllib3 ==2.2.0
